liq/__init__.py
liq/__main__.py
liq/_version.py
liq-0.1.2.dist-info/METADATA
liq-0.1.2.dist-info/WHEEL
liq-0.1.2.dist-info/entry_points.txt
liq-0.1.2.dist-info/licenses/LICENSE
liq-0.1.2.dist-info/RECORD
