Metadata-Version: 2.3
Name: liq
Version: 0.1.2
Summary: Limit Image Quality, pre-commit hook
Author-email: Dries Kennes <dries.kennes@qteal.com>
License: MIT License
License-File: LICENSE
Requires-Python: >=3.8
Requires-Dist: click~=8.1
Requires-Dist: wand~=0.6
